README.md
setup.py
src/flask_sqlalchemy_paging/__init__.py
src/flask_sqlalchemy_paging/decorators.py
src/flask_sqlalchemy_paging/pager.py
src/flask_sqlalchemy_paging.egg-info/PKG-INFO
src/flask_sqlalchemy_paging.egg-info/SOURCES.txt
src/flask_sqlalchemy_paging.egg-info/dependency_links.txt
src/flask_sqlalchemy_paging.egg-info/requires.txt
src/flask_sqlalchemy_paging.egg-info/top_level.txt
test/test_flask_restful.py