Metadata-Version: 1.0
Name: flask-sqlalchemy-paging
Version: 0.0.1
Summary: Painless Paging Flask and SQLAlchemy
Home-page: https://github.com/MichaelWashburnJr/Flask-SQLAlchemy-Paging
Author: Michael Washburn Jr
Author-email: michael@michaelwashburnjr.com
License: UNKNOWN
Platform: UNKNOWN
